cmdline_utils/__init__.py
cmdline_utils/clu.py
cmdline_utils-0.1.dist-info/LICENSE
cmdline_utils-0.1.dist-info/METADATA
cmdline_utils-0.1.dist-info/WHEEL
cmdline_utils-0.1.dist-info/entry_points.txt
cmdline_utils-0.1.dist-info/top_level.txt
cmdline_utils-0.1.dist-info/RECORD
