Metadata-Version: 2.1
Name: cmdline-utils
Version: 0.1
Summary: A CLI tool for helping commands with Groq
Home-page: https://github.com/aletisunil/cmdline_utils
Author: Sunil Aleti
Author-email: iam@sunilaleti.dev
License: UNKNOWN
Keywords: python,groq,llama3 70b
Platform: UNKNOWN
Classifier: Programming Language :: Python :: 3
Classifier: License :: OSI Approved :: MIT License
Classifier: Operating System :: OS Independent
Requires-Python: >=3.8
Requires-Dist: groq
